selenium_utils/__init__.py
selenium_utils/alert.py
selenium_utils/element.py
selenium_utils/exception.py
selenium_utils/navigate.py
selenium_utils/screenshot.py
selenium_utils/tab.py
selenium_utils/user_agent.py
selenium_utils/user_signature.py
selenium_utils-0.2.dist-info/DESCRIPTION.rst
selenium_utils-0.2.dist-info/METADATA
selenium_utils-0.2.dist-info/RECORD
selenium_utils-0.2.dist-info/WHEEL
selenium_utils-0.2.dist-info/metadata.json
selenium_utils-0.2.dist-info/top_level.txt
